swiftserialize/__init__.py
swiftserialize/swiftserialize.py
swiftserialize/classes/csv.py
swiftserialize/classes/json.py
swiftserialize/classes/yaml.py
swiftserialize/examples/middleman.py
swiftserialize/examples/nesting.py
swiftserialize/examples/read.py
swiftserialize/examples/translate.py
swiftserialize/examples/write.py
swiftserialize/examples/data/middleman/input.yaml
swiftserialize/examples/data/middleman/output.bin
swiftserialize/examples/data/nesting/test.yaml
swiftserialize/examples/data/read/input.csv
swiftserialize/examples/data/translate/input.yaml
swiftserialize/examples/data/translate/output.json
swiftserialize/examples/data/write/output.json
swiftserialize-1.3.1.dist-info/METADATA
swiftserialize-1.3.1.dist-info/WHEEL
swiftserialize-1.3.1.dist-info/licenses/LICENSE
swiftserialize-1.3.1.dist-info/RECORD
