Metadata-Version: 2.4
Name: swiftserialize
Version: 1.3.1
Summary: A simple way to read and write structured data. Easily extendable to support custom data formats.
Project-URL: Homepage, https://github.com/SeanYeatts/swiftserialize
Author: Sean Yeatts
License: MIT License
License-File: LICENSE
Classifier: License :: OSI Approved :: MIT License
Classifier: Operating System :: Microsoft :: Windows
Classifier: Programming Language :: Python :: 3
Requires-Python: >=3.8
Requires-Dist: pyyaml>=6.0.0
